<annotation verified="no">
  <folder>test1</folder>
  <filename>0049</filename>
  <path>D:\test1\0049.png</path>
  <source>
    <database>Unknown</database>
  </source>
  <size>
    <width>768</width>
    <height>768</height>
    <depth>3</depth>
  </size>
  <segmented>0</segmented>
  <object>
    <type>robndbox</type>
    <name>ship</name>
    <pose>Unspecified</pose>
    <truncated>0</truncated>
    <difficult>0</difficult>
    <robndbox>
      <cx>575.6587</cx>
      <cy>636.8078</cy>
      <w>274.3088</w>
      <h>39.0382</h>
      <angle>0.59</angle>
    </robndbox>
  </object>
</annotation>
