<annotation verified="no">
  <folder>test1</folder>
  <filename>0192</filename>
  <path>D:\test1\0192.png</path>
  <source>
    <database>Unknown</database>
  </source>
  <size>
    <width>768</width>
    <height>768</height>
    <depth>3</depth>
  </size>
  <segmented>0</segmented>
  <object>
    <type>robndbox</type>
    <name>ship</name>
    <pose>Unspecified</pose>
    <truncated>0</truncated>
    <difficult>0</difficult>
    <robndbox>
      <cx>678.0</cx>
      <cy>81.5</cy>
      <w>161.6153</w>
      <h>28.0268</h>
      <angle>0.19</angle>
    </robndbox>
  </object>
</annotation>
