<annotation verified="no">
  <folder>test1</folder>
  <filename>0069</filename>
  <path>D:\test1\0069.png</path>
  <source>
    <database>Unknown</database>
  </source>
  <size>
    <width>768</width>
    <height>768</height>
    <depth>3</depth>
  </size>
  <segmented>0</segmented>
  <object>
    <type>robndbox</type>
    <name>ship</name>
    <pose>Unspecified</pose>
    <truncated>0</truncated>
    <difficult>0</difficult>
    <robndbox>
      <cx>249.2225</cx>
      <cy>398.1237</cy>
      <w>36.2353</w>
      <h>240.8818</h>
      <angle>2.651593</angle>
    </robndbox>
  </object>
</annotation>
