<annotation verified="no">
  <folder>test1</folder>
  <filename>0320</filename>
  <path>D:\test1\0320.png</path>
  <source>
    <database>Unknown</database>
  </source>
  <size>
    <width>768</width>
    <height>768</height>
    <depth>3</depth>
  </size>
  <segmented>0</segmented>
  <object>
    <type>robndbox</type>
    <name>ship</name>
    <pose>Unspecified</pose>
    <truncated>0</truncated>
    <difficult>0</difficult>
    <robndbox>
      <cx>192.5</cx>
      <cy>278.0</cy>
      <w>30.424</w>
      <h>191.5604</h>
      <angle>3.021593</angle>
    </robndbox>
  </object>
  <object>
    <type>robndbox</type>
    <name>ship</name>
    <pose>Unspecified</pose>
    <truncated>0</truncated>
    <difficult>0</difficult>
    <robndbox>
      <cx>518.0</cx>
      <cy>212.5</cy>
      <w>10.0</w>
      <h>63.0</h>
      <angle>3.021593</angle>
    </robndbox>
  </object>
  <object>
    <type>robndbox</type>
    <name>ship</name>
    <pose>Unspecified</pose>
    <truncated>0</truncated>
    <difficult>0</difficult>
    <robndbox>
      <cx>516.0</cx>
      <cy>598.5</cy>
      <w>20.0</w>
      <h>129.0</h>
      <angle>3.021593</angle>
    </robndbox>
  </object>
</annotation>
